trevorproxy_serverless/__init__.py
trevorproxy_serverless/cli.py
trevorproxy_serverless-0.0.2.dist-info/entry_points.txt
trevorproxy_serverless-0.0.2.dist-info/WHEEL
trevorproxy_serverless-0.0.2.dist-info/METADATA
trevorproxy_serverless-0.0.2.dist-info/RECORD
