Metadata-Version: 2.1
Name: trevorproxy_serverless
Version: 0.0.2
Summary: TREVORproxy wrapper that integrates with aws fargate based proxy cluster
Requires-Python: >=3.6
Requires-Dist: boto3
Requires-Dist: threadlocal_aws
Requires-Dist: trevorproxy
Project-URL: repository, https://github.com/aristosMiliaressis/TREVORproxy_serverless/
